ircpowermeter/__init__.py
ircpowermeter/cli.py
ircpowermeter/meter.py
ircpowermeter-0.2.0.dist-info/METADATA
ircpowermeter-0.2.0.dist-info/WHEEL
ircpowermeter-0.2.0.dist-info/entry_points.txt
ircpowermeter-0.2.0.dist-info/top_level.txt
ircpowermeter-0.2.0.dist-info/RECORD
