Metadata-Version: 2.4
Name: ircpowermeter
Version: 0.2.0
Summary: ImmersionRC RF Power Meter v2 (USB CDC) interface
Author-email: Jonas Estberger <jonas.estberger@lumenradio.com>
License: MIT
Project-URL: Homepage, https://github.com/youruser/immersionrc-rfpm
Project-URL: Issues, https://github.com/youruser/immersionrc-rfpm/issues
Keywords: RF,power-meter,ImmersionRC,dBm,USB,CDC-ACM
Classifier: Programming Language :: Python :: 3
Classifier: License :: OSI Approved :: MIT License
Classifier: Operating System :: POSIX :: Linux
Requires-Python: >=3.8
Requires-Dist: pyserial>=3.5
Provides-Extra: dev
Requires-Dist: build>=1.2.1; extra == "dev"
Requires-Dist: twine>=5.1.1; extra == "dev"
Requires-Dist: wheel; extra == "dev"
